README.rst
setup.cfg
setup.py
pynomer/__init__.py
pynomer/app.py
pynomer/cli.py
pynomer/client.py
pynomer/nomer_utils.py
pynomer/pynomer.py
pynomer.egg-info/PKG-INFO
pynomer.egg-info/SOURCES.txt
pynomer.egg-info/dependency_links.txt
pynomer.egg-info/entry_points.txt
pynomer.egg-info/not-zip-safe
pynomer.egg-info/requires.txt
pynomer.egg-info/top_level.txt