Metadata-Version: 2.1
Name: pynomer
Version: 0.1.6
Summary: A python wrapper for nomer
Home-page: https://github.com/nleguillarme/pynomer
Author: Nicolas Le Guillarme
Author-email: nicolas.leguillarme@univ-grenoble-alpes.fr
License: MIT
Platform: any
Classifier: Development Status :: 4 - Beta
Classifier: License :: OSI Approved :: MIT License
Classifier: Programming Language :: Python
Classifier: Programming Language :: Python :: 3.7
